Metadata-Version: 2.1
Name: shgofast
Version: 0.1.2
Summary: Monkey-patched acceleration for the SHGO optimizer.
Author-email: "Malte J. Ziebarth" <mjz.science@fmvkb.de>
License: MIT License
Project-URL: Homepage, https://github.com/mjziebarth/shgofast
Project-URL: Bug Tracker, https://github.com/mjziebarth/shgofast/issues
Classifier: Development Status :: 4 - Beta
Classifier: Programming Language :: Python :: 3
Classifier: Programming Language :: Cython
Classifier: Programming Language :: C++
Classifier: License :: OSI Approved :: MIT License
Classifier: Intended Audience :: Science/Research
Classifier: Natural Language :: English
Classifier: Operating System :: POSIX :: Linux
Classifier: Topic :: Scientific/Engineering :: Mathematics
License-File: LICENSE
Requires-Dist: numpy
